{"guid":"5F4A23C3-1969-471F-8832-DA4FF0F3BC1B","created":"2019-12-19T13:07:07+00:00","product":"seguro-de-autos-y-pick-ups","answers":{"vehicleBrand":"ALFA ROMEO","vehicleBrandId":"0003","vehicleYear":"2018","vehicleModel":"STELVIO","vehicleModelId":"1974","vehicleVersion":"STELVIO 2.0T 200 HP AWD AT","vehicleGnc":"Sin G.N.C.","vehicleGncID":"0","vehicleGncValue":"0","codInfoAuto":"30141","codVal":"23402","vehicleValue":"3424000","userName":"Renzo Rocca","userEmail":"rrocca@cooperacionseguros.com.ar","userZip":"2600","userIdCity":"1184","userCity":"Venado Tuerto","userState":"Santa Fe","coberturagrua":"limitada","coberturafranquicia":"28000","guid":"5F4A23C3-1969-471F-8832-DA4FF0F3BC1B","planCobertura":"B2","planSuma":"3424000","planPremio":"14628","planPrima":"10229.37","planFechaInicio":"2019-12-19T00:00:00","planFechaFin":"2020-04-19T00:00:00","planPremioMensual":"3657","planPremioReferencia":"19821","planFranquicia":"0","codigoConvenio":"0","bonusMaxConvenio":"0","bonusMaxAntiguedad":"-10","bonusMaxSuma":"-18"},"coopid":"3","coopname":"Cod RC: 01-02-22-32","tripolis":"QE1Py3kwjlPRpdUNPA5HBQ","step_1":{"circulaEn":"Venado Tuerto, Santa Fe (2600)","usoParticular":"1","estaDanado":"0","numeroPatente":"AA025AG","numeroChasis":"0A3S2D6","numeroMotor":"6A9958AS","step":"2","guid":"5F4A23C3-1969-471F-8832-DA4FF0F3BC1B"},"step_2":{"foto-frente":"5F4A23C3-1969-471F-8832-DA4FF0F3BC1B-foto-frente.jpg","foto-atras":"5F4A23C3-1969-471F-8832-DA4FF0F3BC1B-foto-atras.jpg","foto-izquierda":"5F4A23C3-1969-471F-8832-DA4FF0F3BC1B-foto-izquierda.jpg","foto-derecha":"5F4A23C3-1969-471F-8832-DA4FF0F3BC1B-foto-derecha.jpg","product-type":"seguro-de-autos-y-pick-ups","step":"3","guid":"5F4A23C3-1969-471F-8832-DA4FF0F3BC1B"},"step_3":{"customerNombre":"RENZO","customerApellido":"ROCCA","customerFechaNacimiento":{"day":"11","month":"10","year":"1986"},"customerLugarNacimiento":"MARIA TERESA","customerNacionalidad":"1","customerOcupacion":"2343","customerEstadoCivil":"2","customerEmail":"rrocca@cooperacionseguros.com.ar","customerPhonePrefix":"3465","customerPhoneNumber":"002154","customerLocalidadActual":"1184","customerProvincia":"Santa Fe","customerProvinciaId":"13","customerLocalidad":"Venado Tuerto","customerLocalidadId":"1184","customerLocalidadZip":"2600","customerCalle":"Tritripish pish pish","customerNumero":"555","customerPiso":"","customerPuerta":"","num_dni":"32073173","sexo":"M","codcli":"602897\/07","step":"4","guid":"5F4A23C3-1969-471F-8832-DA4FF0F3BC1B"},"step_4":{"cod_productor":"205006\/04","step":"5","guid":"5F4A23C3-1969-471F-8832-DA4FF0F3BC1B"}}