{"guid":"08557A28-DD51-4ABE-BDEA-C84F4DCCF5D5","created":"2020-04-21T11:29:59-03:00","product":"seguro-de-motos","answers":{"vehicleBrand":"HONDA","vehicleYear":"2017","vehicleVersion":"NF 100 WAVE","codInfoAuto":"8810065","codVal":"10771","vehicleValue":"60900","userName":"Leandro A","userEmail":"landra@cooperacionseguros.com.ar","userZip":"2600","userIdCity":"1184","userCity":"Venado Tuerto","userState":"Santa Fe","utmSource":"","utmMedium":"","utmCampaign":"","coberturaap":"35","guid":"08557A28-DD51-4ABE-BDEA-C84F4DCCF5D5","planCobertura":"A","planSuma":"60900","planPremio":"1032","planPrima":"721.67","planFechaInicio":"2020-04-21T00:00:00","planFechaFin":"2020-08-21T00:00:00","planPremioMensual":"258","planPremioReferencia":"1032","planFranquicia":"0","codigoConvenio":"12","bonusMaxConvenio":"0","bonusMaxAntiguedad":"0","bonusMaxSuma":"0","apOnOff":"on","apIdProducto":"122","apIdPlantSuscWebCab":"184","apPremio":"140","apPremioMensual":"35","apPrima":"107.68"},"coopid":"27","coopname":"Cod RC: 73-74-76","tripolis":"Xr+UwBBlC8FV1eJLepQbRg","step_1":{"circulaEn":"Venado Tuerto, Santa Fe (2600)","usoParticular":"1","estaDanado":"0","numeroPatente":"w123fdf","numeroChasis":"ds84fgsd84g","numeroMotor":"50ma01228","step":"2","guid":"08557A28-DD51-4ABE-BDEA-C84F4DCCF5D5"},"step_2":{"foto-frente-derecha":"08557A28-DD51-4ABE-BDEA-C84F4DCCF5D5-foto-frente-derecha.jpg","foto-izquierda-atras":"08557A28-DD51-4ABE-BDEA-C84F4DCCF5D5-foto-izquierda-atras.jfif","foto-numero-motor":"08557A28-DD51-4ABE-BDEA-C84F4DCCF5D5-foto-numero-motor.jpg","foto-numero-chasis":"08557A28-DD51-4ABE-BDEA-C84F4DCCF5D5-foto-numero-chasis.jpg","product-type":"seguro-de-motos","step":"3","guid":"08557A28-DD51-4ABE-BDEA-C84F4DCCF5D5"},"step_3":{"customerNombre":"LEANDRO ANDRES","customerApellido":"ANDRA","customerFechaNacimiento":{"day":"30","month":"3","year":"1994"},"customerLugarNacimiento":"VENADO TUERTO","customerNacionalidad":"1","customerOcupacion":"2346","customerEstadoCivil":"1","customerEmail":"landra@cooperacionseguros.com.ar","customerPhonePrefix":"3462","customerPhoneNumber":"305850","customerLocalidadActual":"1184","customerProvincia":"Santa Fe","customerProvinciaId":"13","customerLocalidad":"Venado Tuerto","customerLocalidadId":"1184","customerLocalidadZip":"2600","customerCalle":"monteagudo ","customerNumero":"126","customerPiso":"","customerPuerta":"","num_dni":"37813834","sexo":"M","codcli":"599213\/03","step":"4","guid":"08557A28-DD51-4ABE-BDEA-C84F4DCCF5D5"},"step_4":{"cod_productor":"560070\/07","step":"5","guid":"08557A28-DD51-4ABE-BDEA-C84F4DCCF5D5"},"step_5":{"step":"6","guid":"08557A28-DD51-4ABE-BDEA-C84F4DCCF5D5","terminos-y-condiciones":"1"}}