{"guid":"39151974-C4E4-4803-BEAE-66ED8B0D384A","created":"2022-10-21T10:10:13-03:00","product":"seguro-de-autos-y-pick-ups","answers":{"userName":null,"userEmail":null,"userZip":null,"userIdCity":null,"userCity":null,"userState":null,"vehicleBrand":null,"vehicleYear":null,"vehicleVersion":null,"codInfoAuto":null,"codVal":null,"vehicleValue":null,"vehicleBrandId":null,"vehicleModel":null,"vehicleModelId":null,"vehicleGnc":null,"vehicleGncID":null,"vehicleGncValue":null},"utmSource":"","utmMedium":"","utmCampaign":"","coopid":"3","coopname":"Cod RC: 01-02-22-32"}