{"guid":"5937E798-EA06-41AA-80DA-3ECE2536DEF7","created":"2019-12-20T16:52:59+00:00","product":"seguro-de-motos","answers":{"vehicleBrand":"HONDA","vehicleYear":"2012","vehicleVersion":"C 105 BIZ","codInfoAuto":"8810070","codVal":"9080","vehicleValue":"0","userName":"Vanesa Gonzalez","userEmail":"vgonzalez@cooperacionseguros.com.ar","userZip":"1601","userIdCity":"10065","userCity":"Isla Martin Garcia","userState":"Buenos Aires","coberturaap":"35","guid":"5937E798-EA06-41AA-80DA-3ECE2536DEF7","planCobertura":"A","planSuma":"0","planPremio":"936","planPrima":"654.54","planFechaInicio":"2019-12-20T00:00:00","planFechaFin":"2020-04-20T00:00:00","planPremioMensual":"234","planPremioReferencia":"936","planFranquicia":"0","codigoConvenio":"0","bonusMaxConvenio":"0","bonusMaxAntiguedad":"0","bonusMaxSuma":"0","apOnOff":"on","apIdProducto":"122","apIdPlantSuscWebCab":"184","apPremio":"140","apPremioMensual":"35","apPrima":"107.68"},"coopid":"27","coopname":"Cod RC: 73-74-76","tripolis":"WtgmAIO5N4zLj5QdabUiEw","step_1":{"circulaEn":"Isla Martin Garcia, Buenos Aires (1601)","usoParticular":"1","estaDanado":"0","numeroPatente":"235jnt","numeroChasis":"bbb","numeroMotor":"bbb","step":"2","guid":"5937E798-EA06-41AA-80DA-3ECE2536DEF7"}}