{"guid":"CDFF6DC9-AAE8-4960-81CF-96D8209ACE95","created":"2022-08-23T04:42:38-03:00","product":"seguro-de-autos-y-pick-ups","answers":{"userName":"Cesar ","userEmail":"saavedra0706@gmail.com","userZip":"6640","userIdCity":"135","userCity":"Bragado","userState":" Buenos Aires","vehicleBrand":"CITROEN","vehicleYear":"2021","vehicleVersion":"C 3 AIRCROSS 1.6 FEEL","codInfoAuto":"110293","codVal":"20944","vehicleValue":2800000,"vehicleBrandId":"0011","vehicleModel":"C3 AIRCROSS","vehicleModelId":"910","vehicleGnc":"Sin G.N.C.","vehicleGncID":"0","vehicleGncValue":"0"},"utmSource":"","utmMedium":"","utmCampaign":"","coopid":"3","coopname":"Cod RC: 01-02-22-32","tripolis":"zz76iFBzU+tbTGavff8ZLA"}